odoo/addons/product_attribute_variant_rules/README.rst
odoo/addons/product_attribute_variant_rules/__init__.py
odoo/addons/product_attribute_variant_rules/__manifest__.py
odoo/addons/product_attribute_variant_rules/i18n/product_attribute_variant_rules.pot
odoo/addons/product_attribute_variant_rules/models/__init__.py
odoo/addons/product_attribute_variant_rules/models/product_attribute_rule.py
odoo/addons/product_attribute_variant_rules/models/product_template.py
odoo/addons/product_attribute_variant_rules/readme/CONTRIBUTORS.rst
odoo/addons/product_attribute_variant_rules/readme/DESCRIPTION.rst
odoo/addons/product_attribute_variant_rules/readme/USAGE.rst
odoo/addons/product_attribute_variant_rules/security/ir.model.access.csv
odoo/addons/product_attribute_variant_rules/static/description/icon.png
odoo/addons/product_attribute_variant_rules/static/description/index.html
odoo/addons/product_attribute_variant_rules/tests/__init__.py
odoo/addons/product_attribute_variant_rules/tests/test_product_attribute_variant_rules.py
odoo/addons/product_attribute_variant_rules/views/product_template_views.xml
odoo14_addon_product_attribute_variant_rules-14.0.1.0.1.dist-info/METADATA
odoo14_addon_product_attribute_variant_rules-14.0.1.0.1.dist-info/WHEEL
odoo14_addon_product_attribute_variant_rules-14.0.1.0.1.dist-info/top_level.txt
odoo14_addon_product_attribute_variant_rules-14.0.1.0.1.dist-info/RECORD
